{
    "about": {
        "version": "5.1.1",
        "displayVersion": "5",
        "date": "2/24/2021"
    },
    "saveState": {
        "mouseorkeyboard": 0,
        "lcbenabled": 0,
        "rcbenabled": 0,
        "mcbenabled": 0,
        "cpspreviousval": 57,
        "keyboardKeys": "",
        "timeoutTypes": 1
    },
    "settings": {
        "general": {
            "runOnStartup": false,
            "startMinimize": false,
            "runWithElevatedPrivliges": false,
            "runHidden": true,
            "mincpsval": 1,
            "maxcpsval": 1000
        },
        "hotKeys": {
            "toggleHotKey": [
                "xbutton1"
            ],
            "lcbHotKey": [
                "a",
                "right_control"
            ],
            "rcbHotKey": [
                "d",
                "right_control"
            ],
            "mcbHotKey": [
                "s",
                "right_control"
            ],
            "lcbHorKey": ""
        },
        "executions": {
            },
            "lin": {},
            "mac": {}
    }
}